{
	"format_version": "1.21.6",
	"credit": "Made with Blockbench",
	"parent": "item/handheld",
	"textures": {
		"layer0": "item/coltpython_origin",
		"particle": "item/coltpython_origin"
	},
	"display": {
		"thirdperson_righthand": {
			"rotation": [0, -90, 25],
			"translation": [0, 1, -0.5],
			"scale": [0.6, 0.6, 0.8]
		},
		"thirdperson_lefthand": {
			"rotation": [0, 90, -25],
			"translation": [0, 1, -0.5],
			"scale": [0.6, 0.6, 0.8]
		},
		"firstperson_righthand": {
			"rotation": [0, -90, 25],
			"translation": [3, 3, -1.25],
			"scale": [1, 1, 1.2]
		},
		"firstperson_lefthand": {
			"rotation": [0, 90, -25],
			"translation": [3, 3, -1.25],
			"scale": [1, 1, 1.2]
		},
		"ground": {
			"rotation": [90, 0, 0],
			"scale": [0.6, 0.6, 0.8]
		},
		"gui": {
			"translation": [1, 0.75, 0]
		},
		"head": {
			"rotation": [0, 0, 25],
			"translation": [0, 12.5, 0],
			"scale": [1, 1, 1.2]
		},
		"fixed": {
			"rotation": [0, 180, 0],
			"translation": [-1.25, 0, 0],
			"scale": [1.1, 1.1, 1.3]
		}
	}
}